README.md
setup.cfg
setup.py
nesmdb/__init__.py
nesmdb/apu.py
nesmdb/convert.py
nesmdb/cycle.py
nesmdb.egg-info/PKG-INFO
nesmdb.egg-info/SOURCES.txt
nesmdb.egg-info/dependency_links.txt
nesmdb.egg-info/entry_points.txt
nesmdb.egg-info/requires.txt
nesmdb.egg-info/top_level.txt
nesmdb/score/__init__.py
nesmdb/score/blndsco.py
nesmdb/score/exprsco.py
nesmdb/score/midi.py
nesmdb/score/rawsco.py
nesmdb/score/seprsco.py
nesmdb/vgm/__init__.py
nesmdb/vgm/bintypes.py
nesmdb/vgm/nd_txt.py
nesmdb/vgm/ndf_nlm.py
nesmdb/vgm/ndr_ndf.py
nesmdb/vgm/vgm_ndr.py
nesmdb/vgm/vgm_simplify.py
nesmdb/vgm/vgm_to_wav.py